AssemblyDataReader/__init__.py
AssemblyDataReader/data.py
AssemblyDataReader-0.2.2.dist-info/METADATA
AssemblyDataReader-0.2.2.dist-info/WHEEL
AssemblyDataReader-0.2.2.dist-info/top_level.txt
AssemblyDataReader-0.2.2.dist-info/RECORD
